observattr/__init__.py
observattr/observattr.py
observattr-21.6.1.dist-info/LICENSE
observattr-21.6.1.dist-info/WHEEL
observattr-21.6.1.dist-info/METADATA
observattr-21.6.1.dist-info/RECORD
